README.md
pyproject.toml
trustgraph/trustgraph_version.py
trustgraph.egg-info/PKG-INFO
trustgraph.egg-info/SOURCES.txt
trustgraph.egg-info/dependency_links.txt
trustgraph.egg-info/requires.txt
trustgraph.egg-info/top_level.txt