Metadata-Version: 2.4
Name: trustgraph
Version: 1.8.2
Summary: TrustGraph provides a means to run a pipeline of flexible AI processing components in a flexible means to achieve a processing pipeline.
Author-email: "trustgraph.ai" <security@trustgraph.ai>
Project-URL: Homepage, https://github.com/trustgraph-ai/trustgraph
Classifier: Programming Language :: Python :: 3
Classifier: Operating System :: OS Independent
Requires-Python: >=3.8
Requires-Dist: trustgraph-base<1.9,>=1.8
Requires-Dist: trustgraph-bedrock<1.9,>=1.8
Requires-Dist: trustgraph-cli<1.9,>=1.8
Requires-Dist: trustgraph-embeddings-hf<1.9,>=1.8
Requires-Dist: trustgraph-flow<1.9,>=1.8
Requires-Dist: trustgraph-vertexai<1.9,>=1.8
